generators/__init__.py
generators/base_module/__init__.py
generators/base_module/base_class.py
generators/cycle_generator/__init__.py
generators/cycle_generator/__main__.py
generators/cycle_generator/cycle_generator_file.py
generators/cycle_generator/out_of_bounds_searcher.py
generators/leak_generator/__init__.py
generators/leak_generator/__main__.py
generators/leak_generator/leak_generator.py
generators/profiling1/__init__.py
generators/profiling1/__main__.py
generators/profiling1/finding_slow_function.py
generators/profiling1/finding_slow_function_in_function.py
generators/profiling1/function_generator.py
generators/profiling1/random_expressions.py
generators/profiling1/variables.py
generators/scripts/__init__.py
generators/scripts/random_words/__init__.py
generators/scripts/random_words/generate_random_words.py
generators/scripts/random_words/random_words_list.txt
generators/scripts/yandex_disk/__init__.py
generators/scripts/yandex_disk/client_wrapper.py
generators/scripts/yandex_disk/upload_yadisk.py
mse_task_generators-0.3.2.dist-info/METADATA
mse_task_generators-0.3.2.dist-info/WHEEL
mse_task_generators-0.3.2.dist-info/entry_points.txt
mse_task_generators-0.3.2.dist-info/top_level.txt
mse_task_generators-0.3.2.dist-info/RECORD
