Metadata-Version: 2.4
Name: mse-task-generators
Version: 0.3.2
Summary: Набор генераторов программ для работы с отладчиками языка С
Requires-Dist: cfile>=0.4.0
Requires-Dist: wonderwords>=2.2.0
Requires-Dist: yadisk>=3.2.0
Requires-Dist: requests>=2.32.3
Requires-Dist: python-dotenv>=1.1.0
Dynamic: description
Dynamic: description-content-type
Dynamic: requires-dist
Dynamic: summary
